MANIFEST.in
setup.py
pysandra_unit.egg-info/PKG-INFO
pysandra_unit.egg-info/SOURCES.txt
pysandra_unit.egg-info/dependency_links.txt
pysandra_unit.egg-info/requires.txt
pysandra_unit.egg-info/top_level.txt
pysandra_unit.egg-info/zip-safe
pysandraunit/__init__.py
pysandraunit/pysandraunit.py
pysandraunit/testcasebase.py
pysandraunit/django/__init__.py
pysandraunit/jar/pysandra-unit.jar
pysandraunit/resources/cu-cassandra.yaml
pysandraunit/unittest/__init__.py