Metadata-Version: 1.0
Name: pysandra-unit
Version: 0.4.1
Summary: Python wrapper for cassandra-unit.
Home-page: https://github.com/Zemanta/pysandra-unit
Author: Jure Ham
Author-email: jure.ham@zemanta.com
License: GPLv3
Platform: any
